{
  "CEP": [
    ["blg", "cep", "cepF"],
    ["blg", "cep", "cep1O"],
    ["blg", "cep", "cepF1O"],
    ["blg", "cep", "cep1O2O"],
    ["blg", "cep", "cep2O3O"],
    ["blg", "cep", "cep1O2O3O"],

    ["gd", "cep", "cepF"],
    ["gd", "cep", "cep1O"],
    ["gd", "cep", "cepF1O"],
    ["gd", "cep", "cep1O2O"],
    ["gd", "cep", "cep2O3O"],
    ["gd", "cep", "cepF1O2O"],
    ["gd", "cep", "cep1O2O3O"],
    
    ["lmc", "cep", "cepF"],
    ["lmc", "cep", "cep1O"],
    ["lmc", "cep", "cep2O"],
    ["lmc", "cep", "cepF1O"],
    ["lmc", "cep", "cep1O2O"],
    ["lmc", "cep", "cep1O3O"],
    ["lmc", "cep", "cep2O3O"],
    ["lmc", "cep", "cepF1O2O"],
    ["lmc", "cep", "cep1O2O3O"],
    
    ["smc", "cep", "cepF"],
    ["smc", "cep", "cep1O"],
    ["smc", "cep", "cep2O"],
    ["smc", "cep", "cepF1O"],
    ["smc", "cep", "cep1O2O"],
    ["smc", "cep", "cep1O2O3O"]
  ],

  "RRLYR": [
    ["blg", "rrlyr", "RRab"],
    ["blg", "rrlyr", "RRc"],
    ["blg", "rrlyr", "RRd"],
    ["blg", "rrlyr", "aRRd"],

    ["gd", "rrlyr", "RRab"],
    ["gd", "rrlyr", "RRc"],
    ["gd", "rrlyr", "RRd"],
    ["gd", "rrlyr", "aRRd"],

    ["lmc", "rrlyr", "RRab"],
    ["lmc", "rrlyr", "RRc"],
    ["lmc", "rrlyr", "RRd"],
    ["lmc", "rrlyr", "aRRd"],

    ["smc", "rrlyr", "RRab"],
    ["smc", "rrlyr", "RRc"],
    ["smc", "rrlyr", "RRd"],
    ["smc", "rrlyr", "aRRd"] 
  ],

  "DSCT": [
    ["blg", "dsct", "dsct"],
    ["gd", "dsct", "dsct"],
    ["lmc", "dsct", "dsct"],
    ["smc", "dsct", "dsct"]
  ],

  "T2CEP": [
    ["blg", "t2cep", "t2cep"],
    ["gd", "t2cep", "t2cep"],
    ["lmc", "t2cep", "t2cep"],
    ["smc", "t2cep", "t2cep"]
  ],

  "ACEP": [
    ["gal", "acep", "acepF"],
    ["gal", "acep", "acep1O"],
    ["lmc", "acep", "acepF"],
    ["lmc", "acep", "acep1O"],
    ["smc", "acep", "acepF"],
    ["smc", "acep", "acep1O"]
  ]
}